template_filler/__init__.py
template_filler-2025.9.26945.dist-info/licenses/LICENSE
template_filler-2025.9.26945.dist-info/METADATA
template_filler-2025.9.26945.dist-info/WHEEL
template_filler-2025.9.26945.dist-info/top_level.txt
template_filler-2025.9.26945.dist-info/RECORD
