Metadata-Version: 2.4
Name: template_filler
Version: 2025.9.26945
Author-email: Eugene Evstafev <hi@eugene.plus>
License: MIT License
Project-URL: Repository, https://pypi.org/project/template_filler/
Requires-Python: >=3.9
License-File: LICENSE
Dynamic: license-file
